.coveragerc
AUTHORS.txt
COPYING.txt
MANIFEST.in
README.rst
ez_setup.py
kittystore.spec
pylintrc
requirements.txt
setup.cfg
setup.py
KittyStore.egg-info/PKG-INFO
KittyStore.egg-info/SOURCES.txt
KittyStore.egg-info/dependency_links.txt
KittyStore.egg-info/entry_points.txt
KittyStore.egg-info/requires.txt
KittyStore.egg-info/top_level.txt
kittystore/__init__.py
kittystore/analysis.py
kittystore/events.py
kittystore/import.py
kittystore/scripts.py
kittystore/scrub.py
kittystore/search.py
kittystore/utils.py
kittystore/caching/__init__.py
kittystore/caching/mailman_user.py
kittystore/caching/mlist.py
kittystore/storm/__init__.py
kittystore/storm/hack_datetime.py
kittystore/storm/model.py
kittystore/storm/store.py
kittystore/storm/utils.py
kittystore/storm/schema/__init__.py
kittystore/storm/schema/patch_1.py
kittystore/storm/schema/patch_10.py
kittystore/storm/schema/patch_11.py
kittystore/storm/schema/patch_12.py
kittystore/storm/schema/patch_13.py
kittystore/storm/schema/patch_14.py
kittystore/storm/schema/patch_15.py
kittystore/storm/schema/patch_16.py
kittystore/storm/schema/patch_17.py
kittystore/storm/schema/patch_18.py
kittystore/storm/schema/patch_2.py
kittystore/storm/schema/patch_3.py
kittystore/storm/schema/patch_4.py
kittystore/storm/schema/patch_5.py
kittystore/storm/schema/patch_6.py
kittystore/storm/schema/patch_7.py
kittystore/storm/schema/patch_8.py
kittystore/storm/schema/patch_9.py
kittystore/storm/schema/utils.py
kittystore/test/__init__.py
kittystore/test/test_analysis.py
kittystore/test/test_caching.py
kittystore/test/test_events.py
kittystore/test/test_scrub.py
kittystore/test/test_storm_model.py
kittystore/test/test_storm_store.py
kittystore/test/test_storm_store_fetch.py
kittystore/test/test_utils.py
kittystore/test/testdata/attachment-1.txt
kittystore/test/testdata/attachment-2.txt
kittystore/test/testdata/attachment-3.txt
kittystore/test/testdata/attachment-4.txt
kittystore/test/testdata/attachment-5.txt
kittystore/test/testdata/html-email-1.txt
kittystore/test/testdata/html-email-2.txt
kittystore/test/testdata/non-ascii-headers.txt
kittystore/test/testdata/payload-iso8859.txt
kittystore/test/testdata/payload-unknown.txt
