Metadata-Version: 1.1
Name: KittyStore
Version: 0.9.3
Summary: A storage engine for GNU Mailman v3 archives
Home-page: https://fedorahosted.org/hyperkitty/
Author: HyperKitty Developers
Author-email: hyperkitty-devel@lists.fedorahosted.org
License: GPLv3
Keywords: email
Platform: UNKNOWN
Classifier: Development Status :: 3 - Alpha
Classifier: License :: OSI Approved :: GNU General Public License v3 (GPLv3)
Classifier: Topic :: Communications :: Email :: Mailing List Servers
Classifier: Programming Language :: Python :: 2
